rust_ok/__init__.py
rust_ok/err.py
rust_ok/exceptions.py
rust_ok/guards.py
rust_ok/ok.py
rust_ok/py.typed
rust_ok/result.py
rust_ok/trace.py
rust_ok-0.2.2.dist-info/WHEEL
rust_ok-0.2.2.dist-info/METADATA
rust_ok-0.2.2.dist-info/RECORD
