Metadata-Version: 2.3
Name: rust-ok
Version: 0.2.2
Summary: Rust-inspired Result/Ok/Err primitives for Python
Keywords: result,error-handling,rust,functional,typing
Author: pesap
Author-email: pesap <pesap@users.noreply.github.com>
License: BSD 3-Clause License
Classifier: Development Status :: 4 - Beta
Classifier: Intended Audience :: Developers
Classifier: License :: OSI Approved :: BSD License
Classifier: Natural Language :: English
Classifier: Programming Language :: Python :: 3.10
Classifier: Programming Language :: Python :: 3.11
Classifier: Programming Language :: Python :: 3.12
Classifier: Programming Language :: Python :: 3.13
Classifier: Programming Language :: Python :: 3.14
Classifier: Typing :: Typed
Requires-Python: >=3.11, <3.15
